beancount_plugins_metadata_spray/plugins/__init__.py
beancount_plugins_metadata_spray/plugins/metadata_spray.py
beancount_plugins_metadata_spray/plugins/metadata_spray_test.py
beancount_plugins_metadata_spray-0.0.1.dist-info/METADATA
beancount_plugins_metadata_spray-0.0.1.dist-info/RECORD
beancount_plugins_metadata_spray-0.0.1.dist-info/WHEEL
beancount_plugins_metadata_spray-0.0.1.dist-info/top_level.txt
