Metadata-Version: 2.1
Name: beancount-plugins-metadata-spray
Version: 0.0.1
Summary: Beancount Plugin to add metadata to accounts
Home-page: https://github.com/seltzered/beancount-plugins-metadata-spray
Author: Vivek Gani
Author-email: me@vivekgani.com
License: GPLv2
Platform: UNKNOWN
Classifier: Development Status :: 3 - Alpha
Classifier: Environment :: Console
Classifier: Intended Audience :: Financial and Insurance Industry
Classifier: Operating System :: OS Independent
Classifier: Programming Language :: Python
Classifier: Programming Language :: Python :: 3
Classifier: Programming Language :: Python :: 3.2
Classifier: Programming Language :: Python :: 3.3
Classifier: Programming Language :: Python :: 3.4
Classifier: Topic :: Utilities
